{
    "_template": "ArticleMain.hbs",

    "datePublished": "Published: December 11, 2016",
    "datePublishedISO": "2016-02-19T16:43:22+00:00",
    "dateModified": "Modified: December 12, 2016",
    "dateModifiedISO": "2016-02-19T17:44:23+00:00",

    "breadcrumbs": {
        "_dataUrl": "Breadcrumbs.json"
    },

    "preHeadline": "Exploration",
    "headline": "After Many Years and 17 Cities, a Pilot Realizes His Dream Journey",
    "subHeadline": "Flying Around the World Without a Drop of Fossil Fuel",
    "byline": "By:",

    "author": {
        "_dataUrl": "Author.json"
    },

    "lead": {
        "_dataUrl": "Image.json",
        "src": "{{image(900,450)}}",
        "width": 900,
        "height": 450
    },

    "body": {
        "_template": "Concatenated.hbs",
        "items": [
            {
                "_template": "RawHtml.hbs",
                "html": "{{paragraphs([3,10])}}"
            },
            {
                "_dataUrl": "EnhancementImageRight.json"
            },
            {
                "_template": "RawHtml.hbs",
                "html": "<h3>Subheadline</h3>"
            },
            {
                "_template": "RawHtml.hbs",
                "html": "{{paragraphs([3,10])}}"
            },
            {
                "_dataUrl": "Enhancement.json"
            },
            {
                "_template": "RawHtml.hbs",
                "html": "{{paragraphs([3,10])}}"
            },
            {
                "_template": "RawHtml.hbs",
                "html": "{{paragraphs([3,10])}}"
            }
        ]
    },

    "tags": {
        "_template": "Concatenated.hbs",
        "delimiter": ",",
        "items": [
            {
                "_template": "Link.hbs",
                "href": "#",
                "body": "Tag 1"
            },
            {
                "_template": "Link.hbs",
                "href": "#",
                "body": "Tag 2"
            },
            {
                "_template": "Link.hbs",
                "href": "#",
                "body": "Tag 3"
            }
        ]
    }
}
